setup.py
py_sql_ext/sql_ext.py
py_sql_ext/transaction.py
py_sql_ext.egg-info/PKG-INFO
py_sql_ext.egg-info/SOURCES.txt
py_sql_ext.egg-info/dependency_links.txt
py_sql_ext.egg-info/requires.txt
py_sql_ext.egg-info/top_level.txt